PyBugReporter/__init__.py
PyBugReporter/_version.py
PyBugReporter/requirements.txt
PyBugReporter/src/BugReporter.py
PyBugReporter/src/DiscordBot.py
PyBugReporter/src/__init__.py
pybugreporter-1.0.11.dist-info/licenses/LICENSE
pybugreporter-1.0.11.dist-info/METADATA
pybugreporter-1.0.11.dist-info/WHEEL
pybugreporter-1.0.11.dist-info/top_level.txt
pybugreporter-1.0.11.dist-info/RECORD
